{"recipes":[{"vegetarian":true,"vegan":false,"glutenFree":true,"dairyFree":true,"veryHealthy":false,"cheap":false,"veryPopular":false,"sustainable":false,"weightWatcherSmartPoints":6,"gaps":"no","lowFodmap":false,"ketogenic":false,"whole30":false,"servings":1,"sourceUrl":"http://www.foodrepublic.com/2012/07/06/root-vegetable-cocktail-recipe","spoonacularSourceUrl":"https://spoonacular.com/root-vegetable-cocktail-493758","aggregateLikes":89,"spoonacularScore":12.0,"healthScore":0.0,"creditText":"Food Republic","sourceName":"Food Republic","pricePerServing":183.3,"extendedIngredients":[{"id":10514037,"aisle":"Alcoholic Beverages","image":"https://spoonacular.com/cdn/ingredients_100x100/vermouth.jpg","consistency":"liquid","name":"gin","amount":1.5,"unit":"ounce","unitShort":"oz","unitLong":"ounces","originalString":"1 1/2 ounce beet-infused Beefeater gin, Infusion: 2 large, raw red beets, peeled and chopped. Put beets in a jar with one liter Beefeater gin, shake, and let sit for three days, shaking daily","metaInformation":["raw","red","with one liter beefeater gin, shake, and let sit for three days, shaking daily","large","peeled"]},{"id":11216,"aisle":"Produce","image":"https://spoonacular.com/cdn/ingredients_100x100/ginger.jpg","consistency":"solid","name":"ginger","amount":0.5,"unit":"ounce","unitShort":"oz","unitLong":"ounces","originalString":"1/2 ounce Domaine de Canton ginger liqueur","metaInformation":[]},{"id":19296,"aisle":"Nut butters, Jams, and Honey;Health Foods","image":"https://spoonacular.com/cdn/ingredients_100x100/honey.jpg","consistency":"liquid","name":"honey","amount":0.5,"unit":"ounce","unitShort":"oz","unitLong":"ounces","originalString":"1/2 ounce tarragon-honey syrup","metaInformation":[]},{"id":9152,"aisle":"Produce","image":"https://spoonacular.com/cdn/ingredients_100x100/lemon-juice.jpg","consistency":"liquid","name":"lemon juice","amount":0.5,"unit":"ounce","unitShort":"oz","unitLong":"ounces","originalString":"1/2 ounce fresh lemon juice","metaInformation":["fresh"]},{"id":2041,"aisle":"Produce","image":"https://spoonacular.com/cdn/ingredients_100x100/tarragon.jpg","consistency":"solid","name":"tarragon leaves","amount":2.0,"unit":"","unitShort":"","unitLong":"","originalString":"2 tarragon leaves","metaInformation":[]}],"id":493758,"title":"Root Vegetable Cocktail","readyInMinutes":45,"image":"https://spoonacular.com/recipeImages/493758-556x370.jpg","imageType":"jpg","cuisines":[],"dishTypes":["beverage","drink"],"diets":["caveman","gluten free","dairy free","lacto ovo vegetarian","primal"],"occasions":[],"winePairing":{"pairedWines":[],"pairingText":"","productMatches":[]},"instructions":"Directions:                                     1. Combine all ingredients in a shaker with ice.2. Shake for 30 seconds and strain into a chilled coup.3. Garnish with tarragon leaves.","analyzedInstructions":[{"name":"","steps":[{"number":1,"step":"Combine all ingredients in a shaker with ice.2. Shake for 30 seconds and strain into a chilled coup.3.","ingredients":[],"equipment":[]},{"number":2,"step":"Garnish with tarragon leaves.","ingredients":[{"id":2041,"name":"tarragon","image":"https://spoonacular.com/cdn/ingredients_100x100/tarragon.jpg"}],"equipment":[]}]}]}]}