{"recipes":[{"vegetarian":false,"vegan":false,"glutenFree":true,"dairyFree":true,"veryHealthy":false,"cheap":false,"veryPopular":true,"sustainable":false,"weightWatcherSmartPoints":2,"gaps":"no","lowFodmap":false,"ketogenic":false,"whole30":true,"servings":4,"preparationMinutes":10,"cookingMinutes":10,"sourceUrl":"http://www.foodnetwork.com/recipes/bacon-braised-mustard-greens.html","spoonacularSourceUrl":"https://spoonacular.com/bacon-braised-mustard-greens-734287","aggregateLikes":399,"spoonacularScore":86.0,"healthScore":19.0,"creditText":"Foodnetwork","sourceName":"Foodnetwork","pricePerServing":72.18,"extendedIngredients":[{"id":1002030,"aisle":"Spices and Seasonings","image":"https://spoonacular.com/cdn/ingredients_100x100/pepper.jpg","consistency":"solid","name":"black pepper","amount":4.0,"unit":"servings","unitShort":"servings","unitLong":"servings","originalString":"Freshly ground black pepper","metaInformation":["black","freshly ground"]},{"id":6194,"aisle":"Canned and Jarred","image":"https://spoonacular.com/cdn/ingredients_100x100/chicken-broth.png","consistency":"liquid","name":"chicken broth","amount":0.5,"unit":"cup","unitShort":"cup","unitLong":"cups","originalString":"1/2 cup chicken broth or stock","metaInformation":[]},{"id":11215,"aisle":"Produce","image":"https://spoonacular.com/cdn/ingredients_100x100/garlic-roasted.jpg","consistency":"solid","name":"garlic","amount":1.0,"unit":"clove","unitShort":"clove","unitLong":"clove","originalString":"1 clove garlic, minced","metaInformation":["minced"]},{"id":1082047,"aisle":"Spices and Seasonings","image":"https://spoonacular.com/cdn/ingredients_100x100/salt.jpg","consistency":"solid","name":"kosher salt","amount":1.0,"unit":"pinch","unitShort":"pinch","unitLong":"pinch","originalString":"Heavy pinch of kosher salt","metaInformation":[]},{"id":9152,"aisle":"Produce","image":"https://spoonacular.com/cdn/ingredients_100x100/lemon-juice.jpg","consistency":"liquid","name":"lemon juice","amount":1.0,"unit":"tablespoon","unitShort":"Tbsp","unitLong":"tablespoon","originalString":"1 tablespoon lemon juice","metaInformation":[]},{"id":11270,"aisle":"Produce","image":"https://spoonacular.com/cdn/ingredients_100x100/chinese-mustard-green.jpg","consistency":"solid","name":"mustard greens","amount":1.0,"unit":"pound","unitShort":"lb","unitLong":"pound","originalString":"1 pound mustard greens (about 1 bunch), tough stems discarded, roughly chopped","metaInformation":["roughly chopped","( 1 bunch)"]},{"id":10310123,"aisle":"Meat","image":"https://spoonacular.com/cdn/ingredients_100x100/raw-bacon.png","consistency":"solid","name":"thick-cut bacon","amount":2.0,"unit":"slices","unitShort":"slices","unitLong":"slices","originalString":"2 slices thick-cut bacon, cut into lardons","metaInformation":["thick-cut","cut into lardons"]}],"id":734287,"title":"Bacon-Braised Mustard Greens","readyInMinutes":20,"image":"https://spoonacular.com/recipeImages/734287-556x370.jpeg","imageType":"jpeg","cuisines":[],"dishTypes":["side dish"],"diets":["caveman","gluten free","dairy free","primal","whole 30"],"occasions":[],"winePairing":{},"instructions":"Heat a large skillet over medium-high heat. Add the bacon and cook until the fat has rendered and the bacon is browned. Add the garlic and cook just until fragrant, about 30 seconds. Add the mustard greens and stir to wilt. Season with salt and pepper. Stir in the chicken broth and bring to a simmer. Cover and let cook until the greens are tender, about 10 minutes. Stir in the lemon juice and serve immediately.","analyzedInstructions":[{"name":"","steps":[{"number":1,"step":"Heat a large skillet over medium-high heat.","ingredients":[],"equipment":[{"id":404645,"name":"frying pan","image":"https://spoonacular.com/cdn/equipment_100x100/pan.png"}]},{"number":2,"step":"Add the bacon and cook until the fat has rendered and the bacon is browned.","ingredients":[{"id":10123,"name":"bacon","image":"https://spoonacular.com/cdn/ingredients_100x100/raw-bacon.png"}],"equipment":[]},{"number":3,"step":"Add the garlic and cook just until fragrant, about 30 seconds.","ingredients":[{"id":11215,"name":"garlic","image":"https://spoonacular.com/cdn/ingredients_100x100/garlic.jpg"}],"equipment":[]},{"number":4,"step":"Add the mustard greens and stir to wilt. Season with salt and pepper. Stir in the chicken broth and bring to a simmer. Cover and let cook until the greens are tender, about 10 minutes. Stir in the lemon juice and serve immediately.","ingredients":[{"id":1102047,"name":"salt and pepper","image":"https://spoonacular.com/cdn/ingredients_100x100/salt-and-pepper.jpg"},{"id":11270,"name":"mustard greens","image":"https://spoonacular.com/cdn/ingredients_100x100/chinese-mustard-green.jpg"},{"id":6194,"name":"chicken broth","image":"https://spoonacular.com/cdn/ingredients_100x100/chicken-broth.png"},{"id":9152,"name":"lemon juice","image":"https://spoonacular.com/cdn/ingredients_100x100/lemon-juice.jpg"}],"equipment":[],"length":{"number":10,"unit":"minutes"}}]}]}]}